zrcl3/desktop_automation.py
zrcl3/dictionary.py
zrcl3/expirable_property.py
zrcl3/github_download.py
zrcl3/image.py
zrcl3/io.py
zrcl3/lazy.py
zrcl3/list_module.py
zrcl3/misc.py
zrcl3/orjson_io_fallback.py
zrcl3/passcrack.py
zrcl3/singleton.py
zrcl3/string.py
zrcl3/subprocess.py
zrcl3/verify_file.py
zrcl3/win_process.py
zrcl3/_internal/__init__.py
zrcl3/_internal/fix_zrcl3_import.py
zrcl3/auto_click/__init__.py
zrcl3/auto_click/ctx.py
zrcl3/auto_click/shell.py
zrcl3/auto_save_dict/on_trigger.py
zrcl3/auto_save_dict/threaded.py
zrcl3/hackthon/__init__.py
zrcl3/hackthon/caller.py
zrcl3/init_generator/__init__.py
zrcl3/init_generator/other_solution.py
zrcl3/mediawiki/__init__.py
zrcl3/mediawiki/parser.py
zrcl3-1.0.6.dist-info/LICENSE
zrcl3-1.0.6.dist-info/METADATA
zrcl3-1.0.6.dist-info/WHEEL
zrcl3-1.0.6.dist-info/top_level.txt
zrcl3-1.0.6.dist-info/RECORD
