Metadata-Version: 2.1
Name: zrcl3
Version: 1.0.6
Summary: zack's common reusable library
Home-page: https://github.com/ZackaryW/py-zrcl3
Author: ZackaryW
Classifier: Programming Language :: Python :: 3
License-File: LICENSE
